Metadata-Version: 2.1
Name: myLibrary-Rodmichael-Marcus
Version: 1.0
Summary: Package containing Linear, nodes and trees
Author: Marcus Kittelson & Rodmichael Umapas
License: UNKNOWN
Platform: UNKNOWN
